Metadata-Version: 2.1
Name: Peptide-Chef
Version: 0.0.7
Summary: Peptide Chef: A Python-based Tool for Proteomic Analyses and Datavisulization
Home-page: https://github.com/TTCooper-PhD
Author: Tyler T. Cooper
Author-email: tcoope2@uwo.ca
License: MIT
Project-URL: Bug Tracker, https://github.com/TTCooper-PhD
Keywords: Proteomics
Platform: UNKNOWN
Classifier: Programming Language :: Python :: 3
Classifier: License :: OSI Approved :: MIT License
Classifier: Operating System :: OS Independent
Classifier: Intended Audience :: Education
Requires-Python: >=3.6
